antchain_sdk_demosdk/__init__.py
antchain_sdk_demosdk/client.py
antchain_sdk_demosdk/models.py
antchain_demosdk-2.0.2.dist-info/LICENSE
antchain_demosdk-2.0.2.dist-info/METADATA
antchain_demosdk-2.0.2.dist-info/WHEEL
antchain_demosdk-2.0.2.dist-info/top_level.txt
antchain_demosdk-2.0.2.dist-info/RECORD
