Metadata-Version: 2.1
Name: antchain-demosdk
Version: 2.0.2
Summary: Ant Chain DEMOSDK SDK Library for Python
Home-page: https://github.com/alipay/antchain-openapi-prod-sdk
Author: Ant Chain SDK
Author-email: sdk-team@alibabacloud.com
License: Apache License 2.0
Keywords: antchain,demosdk
Platform: any
Classifier: Development Status :: 4 - Beta
Classifier: Intended Audience :: Developers
Classifier: License :: OSI Approved :: Apache Software License
Classifier: Programming Language :: Python
Classifier: Programming Language :: Python :: 3
Classifier: Programming Language :: Python :: 3.6
Classifier: Programming Language :: Python :: 3.7
Classifier: Programming Language :: Python :: 3.8
Classifier: Programming Language :: Python :: 3.9
Classifier: Topic :: Software Development
Requires-Python: >=3.6
Requires-Dist: antchain-alipay-util <2.0.0,>=1.0.1
Requires-Dist: alibabacloud-tea-util <1.0.0,>=0.3.13
Requires-Dist: alibabacloud-rpc-util <1.0.0,>=0.0.4
